lbm_caiman_python/__init__.py
lbm_caiman_python/__main__.py
lbm_caiman_python/_version.py
lbm_caiman_python/assembly.py
lbm_caiman_python/batch.py
lbm_caiman_python/collation.py
lbm_caiman_python/default_ops.py
lbm_caiman_python/helpers.py
lbm_caiman_python/lcp_io.py
lbm_caiman_python/stdout.py
lbm_caiman_python/summary.py
lbm_caiman_python/transfer.py
lbm_caiman_python/visualize.py
lbm_caiman_python/util/__init__.py
lbm_caiman_python/util/_store_model.py
lbm_caiman_python/util/exceptions.py
lbm_caiman_python/util/quality.py
lbm_caiman_python/util/signal.py
lbm_caiman_python/util/transform.py
lbm_caiman_python-1.1.0.dist-info/LICENSE.md
lbm_caiman_python-1.1.0.dist-info/METADATA
lbm_caiman_python-1.1.0.dist-info/WHEEL
lbm_caiman_python-1.1.0.dist-info/entry_points.txt
lbm_caiman_python-1.1.0.dist-info/top_level.txt
lbm_caiman_python-1.1.0.dist-info/RECORD
