Metadata-Version: 2.1
Name: lbm_caiman_python
Version: 1.1.0
Summary: Light Beads Microscopy 2P Calcium Imaging Pipeline.
Home-page: https://github.com/millerbrainobservatory/LBM-CaImAn-Python
Author: Your Name Here
Author-email: your_email@example.com
License: BSD-3-Clause
Keywords: Pipeline Numpy Microscopy ScanImage multiROI tiff
Classifier: Development Status :: 3 - Alpha
Classifier: Intended Audience :: Science/Research
Classifier: Programming Language :: Python :: 3 :: Only
License-File: LICENSE.md
Requires-Dist: tifffile
Requires-Dist: numpy<2.0,>=1.24.3
Requires-Dist: numba>=0.57.0
Requires-Dist: scipy>=1.9.0
Requires-Dist: fastplotlib[notebook]
Requires-Dist: matplotlib
Requires-Dist: lcp-mc
Requires-Dist: fabric
Requires-Dist: dask
Requires-Dist: zarr
Provides-Extra: docs
Requires-Dist: sphinx>=6.1.3; extra == "docs"
Requires-Dist: docutils>=0.19; extra == "docs"
Requires-Dist: nbsphinx; extra == "docs"
Requires-Dist: numpydoc; extra == "docs"
Requires-Dist: sphinx-autodoc2; extra == "docs"
Requires-Dist: sphinx_gallery; extra == "docs"
Requires-Dist: sphinx-togglebutton; extra == "docs"
Requires-Dist: sphinx-copybutton; extra == "docs"
Requires-Dist: sphinx_book_theme; extra == "docs"
Requires-Dist: pydata_sphinx_theme; extra == "docs"
Requires-Dist: sphinx_design; extra == "docs"
Requires-Dist: sphinxcontrib-images; extra == "docs"
Requires-Dist: sphinxcontrib-video; extra == "docs"
Requires-Dist: sphinx_tippy; extra == "docs"
Requires-Dist: myst_nb; extra == "docs"
